anomalous_subgroup_detection/__init__.py
anomalous_subgroup_detection/detector.py
anomalous_subgroup_detection/scan_statistics.py
anomalous_subgroup_detection-0.1.0.dist-info/licenses/LICENSE
anomalous_subgroup_detection-0.1.0.dist-info/METADATA
anomalous_subgroup_detection-0.1.0.dist-info/WHEEL
anomalous_subgroup_detection-0.1.0.dist-info/top_level.txt
anomalous_subgroup_detection-0.1.0.dist-info/RECORD
