Metadata-Version: 2.4
Name: anomalous-subgroup-detection
Version: 0.1.0
Summary: A Python library for detecting anomalous subgroups in data using subset scanning techniques
Author-email: Jesmine Omonori <damilolao328@gmail.com>
License-Expression: MIT
Project-URL: Homepage, https://github.com/breadface/anomalous_subgroup_detection
Project-URL: Repository, https://github.com/breadface/anomalous_subgroup_detection
Project-URL: Documentation, https://github.com/breadface/anomalous_subgroup_detection#readme
Project-URL: Bug Tracker, https://github.com/breadface/anomalous_subgroup_detection/issues
Keywords: anomaly-detection,statistics,data-analysis,scan-statistics,subgroup-detection
Classifier: Development Status :: 4 - Beta
Classifier: Intended Audience :: Developers
Classifier: Intended Audience :: Science/Research
Classifier: Operating System :: OS Independent
Classifier: Programming Language :: Python :: 3
Classifier: Programming Language :: Python :: 3.8
Classifier: Programming Language :: Python :: 3.9
Classifier: Programming Language :: Python :: 3.10
Classifier: Programming Language :: Python :: 3.11
Classifier: Programming Language :: Python :: 3.12
Classifier: Programming Language :: Python :: 3.13
Classifier: Topic :: Scientific/Engineering :: Information Analysis
Classifier: Topic :: Software Development :: Libraries :: Python Modules
Requires-Python: >=3.8
License-File: LICENSE
Requires-Dist: numpy>=1.20.0
Requires-Dist: pandas>=1.3.0
Requires-Dist: scipy>=1.7.0
Provides-Extra: dev
Requires-Dist: pytest>=6.0; extra == "dev"
Requires-Dist: pytest-cov>=2.0; extra == "dev"
Dynamic: license-file
